aiextras.py
aiextras-2.3.dist-info/LICENSE
aiextras-2.3.dist-info/METADATA
aiextras-2.3.dist-info/WHEEL
aiextras-2.3.dist-info/top_level.txt
aiextras-2.3.dist-info/RECORD
