Metadata-Version: 2.1
Name: aiextras
Version: 2.3
Summary: AI2LAB Programs
Author: AnupamKris
Classifier: Programming Language :: Python :: 3
Classifier: License :: OSI Approved :: MIT License
Classifier: Operating System :: OS Independent
Requires-Python: >=3.6
License-File: LICENSE
